pinkhash/__init__.py
pinkhash/exception.py
pinkhash/lang.py
pinkhash/main.py
pinkhash/languages/nato.py
pinkhash/languages/rfc1751.py
pinkhash/languages/bip39/__init__.py
pinkhash/languages/bip39/chinese_simplified.txt
pinkhash/languages/bip39/chinese_traditional.txt
pinkhash/languages/bip39/czech.txt
pinkhash/languages/bip39/english.txt
pinkhash/languages/bip39/french.txt
pinkhash/languages/bip39/italian.txt
pinkhash/languages/bip39/japanese.txt
pinkhash/languages/bip39/korean.txt
pinkhash/languages/bip39/portuguese.txt
pinkhash/languages/bip39/spanish.txt
pinkhash/languages/eng1/__init__.py
pinkhash/languages/eng1/eng1-adjective.txt
pinkhash/languages/eng1/eng1-nouns.txt
pinkhash/languages/eng1/eng1_gen.py
pinkhash-0.0.7.dist-info/METADATA
pinkhash-0.0.7.dist-info/WHEEL
pinkhash-0.0.7.dist-info/entry_points.txt
pinkhash-0.0.7.dist-info/licenses/LICENSE
pinkhash-0.0.7.dist-info/RECORD
