Metadata-Version: 2.3
Name: pinkhash
Version: 0.0.7
Summary: Convert any hash/data into human-friendly memorable phrase (numerous ways)
Project-URL: Homepage, https://github.com/yaroslaff/pinkhash
Project-URL: Issues, https://github.com/yaroslaff/pinkhash/issues
Author-email: Yaroslav Polyakov <yaroslaff@gmail.com>
License-File: LICENSE
Keywords: BIP39,ICAO,NATO,RFC1751,convert,elephant,english,hash,memorize,mnemonic,natural,natural language,pink,pinkelephant,pinkhash,vivid,words
Classifier: License :: OSI Approved :: MIT License
Classifier: Operating System :: OS Independent
Classifier: Programming Language :: Python :: 3
Classifier: Topic :: Security :: Cryptography
Requires-Python: >=3.8
